pype_bin/__init__.py
pype_bin/__main__.py
pype_bin/lib/__init__.py
pype_bin/lib/subr.py
pype_bin/py.types
pype_bin/template.py.jinja
pype_bin-0.1.2.dist-info/LICENSE
pype_bin-0.1.2.dist-info/METADATA
pype_bin-0.1.2.dist-info/WHEEL
pype_bin-0.1.2.dist-info/entry_points.txt
pype_bin-0.1.2.dist-info/RECORD
