Metadata-Version: 2.1
Name: pype-bin
Version: 0.1.2
Summary: 
License: Apache-2.0
Author: Naoya Yamashita
Author-email: conao3@gmail.com
Requires-Python: >=3.11,<4.0
Classifier: License :: OSI Approved :: Apache Software License
Classifier: Programming Language :: Python :: 3
Classifier: Programming Language :: Python :: 3.11
Requires-Dist: jinja2 (>=3.1.2,<4.0.0)
